[
  {
    "data": [
      {
        "word": "ญ",
        "definition": "[ยอ] พยัญชนะตัวที่ ๑๓ เรียกว่า ญอ หญิง เป็นอักษรต่ำ ใช้เป็นพยัญชนะต้น และเป็นตัวสะกดในมาตรากนหรือแม่กน เช่น ปัญญา สัญชาติ ผจญ โคโลญ."
      }
    ],
    "word": "ญ"
  },
  {
    "data": [
      {
        "word": "ญาติ, ญาติ-",
        "definition": "[ยาด, ยาติ-, ยาดติ-] น. คนในวงศ์วานที่ยังนับรู้กันได้ทางเชื้อสายฝ่ายพ่อหรือฝ่ายแม่. (ป.). ลูกคำของ \"ญาติ, ญาติ-\" คือ [[lookup:ญาติกา]] [[lookup:ญาติกาญาติโก]] [[lookup:ญาติโกโหติกา]] [[lookup:ญาติดี]] [[lookup:ญาติธรรม]] [[lookup:ญาติมิตร]] [[lookup:ญาติสืบสายโลหิต]] [[lookup:ญาติสืบสาโลหิต]]"
      }
    ],
    "word": "ญาติ"
  },
  {
    "data": [
      {
        "word": "ญาติ, ญาติ-",
        "definition": "[ยาด, ยาติ-, ยาดติ-] น. คนในวงศ์วานที่ยังนับรู้กันได้ทางเชื้อสายฝ่ายพ่อหรือฝ่ายแม่. (ป.). ลูกคำของ \"ญาติ, ญาติ-\" คือ [[lookup:ญาติกา]] [[lookup:ญาติกาญาติโก]] [[lookup:ญาติโกโหติกา]] [[lookup:ญาติดี]] [[lookup:ญาติธรรม]] [[lookup:ญาติมิตร]] [[lookup:ญาติสืบสายโลหิต]] [[lookup:ญาติสืบสาโลหิต]]"
      }
    ],
    "word": "ญาติ-"
  },
  {
    "data": [
      {
        "word": "ญาติกา",
        "definition": "[ยาดติ-]  (ปาก) น. ญาติ. แม่คำของ \"ญาติกา\" คือ [[lookup:ญาติ]] [[lookup:ญาติ-]]"
      }
    ],
    "word": "ญาติกา"
  },
  {
    "data": [
      {
        "word": "ญาติกาญาติโก, ญาติโกโหติกา",
        "definition": "[ยาดติ-]  (ปาก) น. เหล่าเครือญาติ. แม่คำของ \"ญาติกาญาติโก, ญาติโกโหติกา\" คือ [[lookup:ญาติ]] [[lookup:ญาติ-]]"
      }
    ],
    "word": "ญาติกาญาติโก"
  },
  {
    "data": [
      {
        "word": "ญาติกาญาติโก, ญาติโกโหติกา",
        "definition": "[ยาดติ-]  (ปาก) น. เหล่าเครือญาติ. แม่คำของ \"ญาติกาญาติโก, ญาติโกโหติกา\" คือ [[lookup:ญาติ]] [[lookup:ญาติ-]]"
      }
    ],
    "word": "ญาติโกโหติกา"
  },
  {
    "data": [
      {
        "word": "ญาติดี",
        "definition": "ก. ทำเป็นดีด้วย, ทำดีด้วย, เช่น เธอไม่ต้องมาญาติดีกับฉัน. แม่คำของ \"ญาติดี\" คือ [[lookup:ญาติ]] [[lookup:ญาติ-]]"
      }
    ],
    "word": "ญาติดี"
  },
  {
    "data": [
      {
        "word": "ญาติธรรม",
        "definition": "[ยาดติ-] น. ญาติในทางธรรม, ผู้มีความสัมพันธ์กันฉันญาติเพราะนับถือศาสนาหรือลัทธิของศาสนาร่วมกัน. แม่คำของ \"ญาติธรรม\" คือ [[lookup:ญาติ]] [[lookup:ญาติ-]]"
      }
    ],
    "word": "ญาติธรรม"
  },
  {
    "data": [
      {
        "word": "ญาติมิตร",
        "definition": "(๑)  [ยาด-] น. ญาติและเพื่อนฝูง. (๒)  [ยาด-]  (ปาก) ก. ร่วมวงเล่นไพ่ตอง เช่น ไปญาติมิตรกัน. แม่คำของ \"ญาติมิตร\" คือ [[lookup:ญาติ]] [[lookup:ญาติ-]]"
      }
    ],
    "word": "ญาติมิตร"
  },
  {
    "data": [
      {
        "word": "ญาติสืบสาโลหิต,ญาติสืบสายโลหิต",
        "definition": "(กฎ) น. ญาติที่มีความสัมพันธ์กันทางสายเลือด. แม่คำของ \"ญาติสืบสาโลหิต,ญาติสืบสายโลหิต\" คือ [[lookup:ญาติ]] [[lookup:ญาติ-]]"
      }
    ],
    "word": "ญาติสืบสายโลหิต"
  },
  {
    "data": [
      {
        "word": "ญาติสืบสาโลหิต,ญาติสืบสายโลหิต",
        "definition": "(กฎ) น. ญาติที่มีความสัมพันธ์กันทางสายเลือด. แม่คำของ \"ญาติสืบสาโลหิต,ญาติสืบสายโลหิต\" คือ [[lookup:ญาติ]] [[lookup:ญาติ-]]"
      }
    ],
    "word": "ญาติสืบสาโลหิต"
  },
  {
    "data": [
      {
        "word": "ญญ่าย",
        "definition": "[ยะย่าย]  (แบบ) ว. แตกจากหมู่, กระจัดกระจาย, ในคำว่า หนีญญ่ายพ่ายจแจ้น (จารึกสยาม)."
      }
    ],
    "word": "ญญ่าย"
  },
  {
    "data": [
      {
        "word": "ญิบ",
        "definition": "(ถิ่น-พายัพ) ว. สอง เช่น ญิบพัน ว่า สองพัน, หญิบ ก็ใช้."
      }
    ],
    "word": "ญิบ"
  },
  {
    "data": [
      {
        "word": "ญี่",
        "definition": "(โบ) น. สอง, เรียกลูกชายคนที่ ๒ ว่า ลูกญี่, คู่กับ ลูกหญิงคนที่ ๒ ว่า ลูกอี่."
      }
    ],
    "word": "ญี่"
  },
  {
    "data": [
      {
        "word": "ญี่ปุ่น",
        "definition": "น. ชื่อประเทศและชนชาติหนึ่งอยู่ในหมู่เกาะทางทิศตะวันออกของประเทศจีน."
      }
    ],
    "word": "ญี่ปุ่น"
  },
  {
    "data": [
      {
        "word": "เญยธรรม, ไญยธรรม",
        "definition": "[เยยฺยะทำ, ไยยะทำ]  (แบบ) น. ธรรมที่ควรรู้. (ป. เยฺย + ส. ธรฺม)."
      }
    ],
    "word": "เญยธรรม"
  },
  {
    "data": [
      {
        "word": "เญยธรรม, ไญยธรรม",
        "definition": "[เยยฺยะทำ, ไยยะทำ]  (แบบ) น. ธรรมที่ควรรู้. (ป. เยฺย + ส. ธรฺม)."
      }
    ],
    "word": "ไญยธรรม"
  },
  {
    "data": [
      {
        "word": "ญวน ๑",
        "definition": "น. ชื่อประเทศและชนชาติหนึ่งอยู่ทางทิศใต้ของประเทศจีน และทางทิศตะวันออกของประเทศลาวและเขมร, ปัจจุบันเรียกว่า เวียดนาม. ลูกคำของ \"ญวน ๑\" คือ [[lookup:ญวนหก]]"
      },
      {
        "word": "ญวน ๒",
        "definition": "น. ดู ใบขนุน (๑) . ความหมายที่เกี่ยวข้อง ดู [[lookup:ใบขนุน]]"
      }
    ],
    "word": "ญวน"
  },
  {
    "data": [
      {
        "word": "ญวนหก",
        "definition": "น. การแสดงกายกรรมอย่างหนึ่ง. แม่คำของ \"ญวนหก\" คือ [[lookup:ญวน ๑]]"
      }
    ],
    "word": "ญวนหก"
  },
  {
    "data": [
      {
        "word": "ญัตติ",
        "definition": "(๑) น. คำสวดประกาศเป็นภาษาบาลี เสนอให้ที่ประชุมสงฆ์ทราบเพื่อทำกิจของสงฆ์ร่วมกัน, คำเผดียงสงฆ์ ก็ว่า (ป.). (๒)  (กฎ) ข้อเสนอเพื่อให้มีการดำเนินการอย่างหนึ่งอย่างใดในกิจการของสภาที่ทำหน้าที่นิติบัญญัติ (ป.). (๓) น. ข้อเสนอเพื่อลงมติ เช่น ผู้แทนราษฎรเสนอญัตติเข้าสู่สภาเพื่อขอให้ที่ประชุมลงมติว่าจะเห็นชอบด้วยหรือไม่ (ป.). (๔) น. หัวข้อโต้วาที เช่น โต้วาทีในญัตติว่า ขุนช้างดีกว่าขุนแผน. (ป.). ลูกคำของ \"ญัตติ\" คือ [[lookup:ญัตติขอเปิดอภิปรายทั่วไป]]"
      }
    ],
    "word": "ญัตติ"
  },
  {
    "data": [
      {
        "word": "ญัตติขอเปิดอภิปรายทั่วไป",
        "definition": "(กฎ) น. มาตรการสำคัญอย่างหนึ่งของระบบรัฐสภาที่ฝ่ายนิติบัญญัติใช้ควบคุมและตรวจสอบฝ่ายบริหาร และฝ่ายบริหารใช้ประโยชน์จากฝ่ายนิติบัญญัติในการรับฟังความคิดเห็นจากฝ่ายนิติบัญญัติ. แม่คำของ \"ญัตติขอเปิดอภิปรายทั่วไป\" คือ [[lookup:ญัตติ]]"
      }
    ],
    "word": "ญัตติขอเปิดอภิปรายทั่วไป"
  },
  {
    "data": [
      {
        "word": "ญาณ, ญาณ-",
        "definition": "[ยาน, ยานะ-, ยานนะ-] น. ปัญญาหยั่งรู้หรือกำหนดรู้ที่เกิดจากอำนาจสมาธิ, ความสามารถหยั่งรู้เป็นพิเศษ. (ป.; ส. ชฺาน). ลูกคำของ \"ญาณ, ญาณ-\" คือ [[lookup:ญาณวิทยา]] [[lookup:ญาณศาสตร์]]"
      }
    ],
    "word": "ญาณ"
  },
  {
    "data": [
      {
        "word": "ญาณ, ญาณ-",
        "definition": "[ยาน, ยานะ-, ยานนะ-] น. ปัญญาหยั่งรู้หรือกำหนดรู้ที่เกิดจากอำนาจสมาธิ, ความสามารถหยั่งรู้เป็นพิเศษ. (ป.; ส. ชฺาน). ลูกคำของ \"ญาณ, ญาณ-\" คือ [[lookup:ญาณวิทยา]] [[lookup:ญาณศาสตร์]]"
      }
    ],
    "word": "ญาณ-"
  },
  {
    "data": [
      {
        "word": "ญาณวิทยา",
        "definition": "[ยานะวิดทะยา, ยานนะวิดทะยา] น. ปรัชญาสาขาหนึ่งว่าด้วยบ่อเกิด ลักษณะ หน้าที่ ประเภท ระเบียบวิธี และความสมเหตุสมผลของความรู้. (อ. epistemology). แม่คำของ \"ญาณวิทยา\" คือ [[lookup:ญาณ]] [[lookup:ญาณ-]]"
      }
    ],
    "word": "ญาณวิทยา"
  },
  {
    "data": [
      {
        "word": "ญาณศาสตร์",
        "definition": "[ยานะสาด, ยานนะสาด] น. ตำราพยากรณ์. (ป. าณ + ส. ศาสฺตฺร). แม่คำของ \"ญาณศาสตร์\" คือ [[lookup:ญาณ]] [[lookup:ญาณ-]]"
      }
    ],
    "word": "ญาณศาสตร์"
  }
]
